dashboard/__init__.py
dashboard/manage.py
dashboard/jobs/__init__.py
dashboard/jobs/admin.py
dashboard/jobs/apps.py
dashboard/jobs/models.py
dashboard/jobs/tests.py
dashboard/jobs/urls.py
dashboard/jobs/views.py
dashboard/jobs/migrations/0001_initial.py
dashboard/jobs/migrations/0002_job_job_id.py
dashboard/jobs/migrations/0003_auto_20190222_1601.py
dashboard/jobs/migrations/0004_auto_20190222_1602.py
dashboard/jobs/migrations/0005_auto_20190222_1602.py
dashboard/jobs/migrations/0006_auto_20190222_1606.py
dashboard/jobs/migrations/0007_auto_20190222_1616.py
dashboard/jobs/migrations/__init__.py
dashboard/unittests/__init__.py
dashboard/unittests/admin.py
dashboard/unittests/apps.py
dashboard/unittests/models.py
dashboard/unittests/tests.py
dashboard/unittests/urls.py
dashboard/unittests/views.py
dashboard/unittests/migrations/__init__.py
anna_dashboard-0.0.2.dist-info/METADATA
anna_dashboard-0.0.2.dist-info/WHEEL
anna_dashboard-0.0.2.dist-info/top_level.txt
anna_dashboard-0.0.2.dist-info/RECORD
